<data>
    <xpath expr="/form/label[@name=&quot;currency&quot;]" position="replace">
    </xpath>
    <xpath expr="/form/field[@name=&quot;currency&quot;]" position="replace">
    </xpath>
    <xpath expr="/form/label[@name=&quot;amount&quot;]" position="replace">
    </xpath>
    <xpath expr="/form/field[@name=&quot;amount&quot;]" position="replace">
    </xpath>
    <xpath expr="/form/label[@name=&quot;description&quot;]" position="replace">
    </xpath>
    <xpath expr="/form/field[@name=&quot;description&quot;]" position="replace">
    </xpath>
    <xpath expr="/form/label[@name=&quot;date&quot;]" position="replace">
    </xpath>
    <xpath expr="/form/field[@name=&quot;date&quot;]" position="replace">
    </xpath>
    <!--
    <xpath expr="/form/label[@name=&quot;journal&quot;]" position="before">
        <label name="currency"/>
        <field name="currency" readonly="1"/>
        <label name="date"/>
        <field name="date" readonly="1"/>
        <label name="description"/>
        <field name="description"/>
        <label name="amount"/>
        <field name="amount"/>
        <label name="receipt"/>
        <field name="receipt"/>
    </xpath>
    -->
    <xpath expr="/form/field[@name=&quot;journal&quot;]" position="after">
        <label name="third_party"/>
        <field name="third_party" colspan="3"/>
    	<label name="is_ticket"/>
    	<field name="is_ticket"/>
    	<label name="ticket"/>
    	<field name="ticket"/>
    </xpath> 
    
</data>